[
  {
    "title": "Grocery List / Stores",
    "hashtags": [],
    "description": "Bread flour - Instant dry yeast - Extra-virgin olive oil, banana shallots - 4 garlic cloves.",
    "subtitle": " ",
    "todolist": [],
    "friends": [],
    "added": "1 min"
  },
  {
    "title": "Books to read 🌶️",
    "hashtags": ["#books", "#needtoread"],
    "description": "Cheers to the books we've been meaning to read all these years and should probably start at some point",
    "subtitle": " ",
    "todolist": [],
    "friends": [],
    "added": "5 min"
  },
  {
    "title": "Write down your ideas 💡",
    "hashtags": ["#ideas", "#to-do's", "#morning"],
    "description": "Sometimes, on mornings, when servers at A16 are announcing the specials, you can almost feel the excitement at the table when the waiters say 'And of course, since it's Monday... we have meatballs.' says Shelley Lingren.",
    "subtitle": "Morning",
    "todolist": [
      {
        "title": "setup meeting with Rachel",
        "checked": true
      },
      {
        "title": "apply at Braintree",
        "checked": false
      },
      {
        "title": "check to-dos",
        "checked": false
      },
      {
        "title": "check reservations",
        "checked": true
      }
    ],
    "friends": ["Man", "Woman1", "Woman2"],
    "added": "1 day"
  },
  {
    "title": "Curried Carrot Soup",
    "hashtags": ["#recipes", "#recipes/savory", "#recipes/soups"],
    "description": "Curried Carrot and Fennel Soup with Turmeric and Ginger",
    "subtitle": "Recipe",
    "todolist": [
      {
        "title": "Carrots",
        "checked": true
      },
      {
        "title": "Fennel",
        "checked": false
      },
      {
        "title": "Ginger",
        "checked": true
      },
      {
        "title": "Turmeric",
        "checked": true
      },
      {
        "title": "Garlic",
        "checked": true
      },
      {
        "title": "Garam Masala",
        "checked": true
      }
    ],
    "friends": ["Woman1"],
    "added": "2 days"
  },
  {
    "title": "Mexican Tomatillo Scrambled Eggs 🌶️",
    "hashtags": ["#recipes", "#recipes/savory"],
    "description": "This is a great way to use up leftover salsa verde. If you don’t have any, you can make your own or use regular tomato salsa.",
    "subtitle": "Recipe",
    "todolist": [
      {
        "title": "Tomatillos",
        "checked": false
      },
      {
        "title": "Onion",
        "checked": true
      },
      {
        "title": "Eggs",
        "checked": true
      },
      {
        "title": "Lime",
        "checked": false
      },
      {
        "title": "Garlic",
        "checked": true
      },
      {
        "title": "Cumin",
        "checked": true
      }
    ],
    "friends": [],
    "added": "5 days"
  }
]
